linkcutter/__init__.py
linkcutter/cutter.py
linkcutter-0.0.1a2.dist-info/LICENSE
linkcutter-0.0.1a2.dist-info/WHEEL
linkcutter-0.0.1a2.dist-info/METADATA
linkcutter-0.0.1a2.dist-info/RECORD
