Metadata-Version: 2.1
Name: linkcutter
Version: 0.0.1a2
Summary: Make link shorter using cutt.ly API
Home-page: https://github.com/MorningStar-png/linkcutter-py
License: UNKNOWN
Author: Ilia Fedorovich
Author-email: workplaceilfed@gmail.com
Requires-Python: >=3.8
Classifier: License :: OSI Approved :: MIT License
Classifier: Programming Language :: Python :: 3
